aiohttp_wsgi/__init__.py
aiohttp_wsgi/__main__.py
aiohttp_wsgi/py.typed
aiohttp_wsgi/utils.py
aiohttp_wsgi/wsgi.py
aiohttp_wsgi-0.10.0.dist-info/LICENSE
aiohttp_wsgi-0.10.0.dist-info/METADATA
aiohttp_wsgi-0.10.0.dist-info/WHEEL
aiohttp_wsgi-0.10.0.dist-info/entry_points.txt
aiohttp_wsgi-0.10.0.dist-info/top_level.txt
aiohttp_wsgi-0.10.0.dist-info/RECORD
